readme_generator/__init__.py
readme_generator/emoji_map.py
readme_generator/generate_readme.py
readme_generator/readme_builder.py
readme_generator/repo_structure.py
tree_readme-2.2.0.dist-info/METADATA
tree_readme-2.2.0.dist-info/WHEEL
tree_readme-2.2.0.dist-info/top_level.txt
tree_readme-2.2.0.dist-info/RECORD
